Metadata-Version: 1.0
Name: django-competition
Version: 0.2.0
Summary: Simple vote mechanism for a competition
Home-page: UNKNOWN
Author: Jacek Bzdak
Author-email: jacek@askesis.pl
License: Apache
Platform: UNKNOWN
